MIPS_Multi_Cycle/ALU.v
/*

	File name    : 
	LastEditors  : H
	LastEditTime : 2021-10-28 16:44:49
	Last Version : 1.0
	Description  : 
	
	----------------------------------------------------------------------------------------
	
	Author       : H
	Date         : 2021-10-28 16:44:48
	FilePath     : \MIPS_Single\ALU.v
	Copyright 2021 H, All Rights Reserved. 

*/
module ALU(
    // System Clock
    input               clk,
    // User Interface
    input               ALUSrcA,
    input       [1:0]   ALUSrcB,
    input       [31:0]  A,
    input       [31:0]  B,
    input       [31:0]  PC,
    input       [31:0]  SignImm,

    // input       [31:0]  SrcA,
    // input       [31:0]  SrcB,

    input       [2:0]   ALUControl,
    output  reg [31:0]  ALUOut,
    output  reg [31:0]  ALUResult,
    output              Zero
);
    reg [31:0]  SrcA,SrcB;

/*******************************************************************************
 *                                 Main Code
*******************************************************************************/
    
    assign Zero = (ALUResult) ? 1'b0 : 1'b1;
    always @(*) begin
        SrcA = ALUSrcA ? A : PC;
        case(ALUSrcB)
            2'b00: SrcB = B;
            2'b01: SrcB = 32'd4;
            2'b10: SrcB = SignImm;
            2'b11: SrcB = SignImm << 2;
        endcase
    end

    always @(*) begin
        case (ALUControl)
            3'b010 : begin
                ALUResult = SrcA + SrcB;
            end 
            3'b110 : begin
                ALUResult = SrcA - SrcB;
            end
            3'b000 : ALUResult = SrcA & SrcB;
            3'b001 : ALUResult = SrcA | SrcB;
            3'b111 : ALUResult = (SrcA < SrcB) ? 32'b1 : 32'b0;
            default: ;
        endcase
    end

    always @(posedge clk) begin
        ALUOut <= ALUResult;
    end


endmodule

MIPS_Multi_Cycle/ALU_Control_Unit.v
/*

	File name    : ALU_Control_Unit
	LastEditors  : H
	LastEditTime : 2021-10-29 19:33:47
	Last Version : 1.0
	Description  : 
	
	----------------------------------------------------------------------------------------
	
	Author       : H
	Date         : 2021-10-29 19:33:45
	FilePath     : \MIPS_Single_Cycle\ALU_Control_Unit.v
	Copyright 2021 H, All Rights Reserved. 

*/
module ALU_Control_Unit(
    // System Clock

    // User Interface
    input       [5:0]   Funct,
    input       [1:0]   ALUOp,
    output  reg [2:0]   ALUControl
);

/*******************************************************************************
 *                                 Main Code
*******************************************************************************/

    always @(*) begin
        case (ALUOp)
            2'b00: ALUControl = 3'b010;
            2'b10: begin
                case (Funct)
                    6'b100000 : ALUControl = 3'b010;
                    6'b100010 : ALUControl = 3'b110;
                    6'b100100 : ALUControl = 3'b000;
                    6'b100101 : ALUControl = 3'b001;
                    6'b101010 : ALUControl = 3'b111;
                endcase
            end
            2'b01: ALUControl = 3'b110;
            default: ;
        endcase
    end


endmodule

MIPS_Pipeline/Imm_Sign_Extend.v
/*

	File name    : Imm_Sign_Extend
	LastEditors  : H
	LastEditTime : 2021-11-04 21:50:55
	Last Version : 1.0
	Description  : According to Sign bit, Extend Imm to 32bits
	
	----------------------------------------------------------------------------------------
	
	Author       : H
	Date         : 2021-11-03 21:01:39
	FilePath     : \MIPS_Pipeline\Imm_Sign_Extend.v
	Copyright 2021 H, All Rights Reserved. 

*/

module Imm_Sign_Extend(
    // User Interface
    input       [15:0]  Immediate,

    output      [31:0]  SignImm
);
    assign  SignImm = {{16{Immediate[15]}}, Immediate[15:0]};
endmodule

MIPS_Multi_Cycle/Reg_File.v
/*

	File name    : Reg_File
	LastEditors  : H
	LastEditTime : 2021-10-28 16:37:57
	Last Version : 1.0
	Description  : 
	
	----------------------------------------------------------------------------------------
	
	Author       : H
	Date         : 2021-10-28 16:37:55
	FilePath     : \MIPS_Single\Reg_File.v
	Copyright 2021 H, All Rights Reserved. 

*/
module Reg_File (
    input               clk,
    input       [4:0]   A1,
    input       [4:0]   A2,
    input       [4:0]   A3,
    input               RegWrite,
    input       [31:0]  WD3,
    
    output  reg [31:0]  A,
    output  reg [31:0]  B

);
    // lw : load word instr [op(6bit) rs(5bit) rd(5bit) imm(16bit)]
    wire [31:0] RD1,RD2;
    reg [31:0]  ROM [31:0];
    initial begin
        ROM[0] <= 32'b0;
        ROM[1] <= 32'b0;
        ROM[2] <= 32'b0;
        ROM[3] <= 32'b0;
        ROM[4] <= 32'b0;
        ROM[5] <= 32'b0;
        ROM[6] <= 32'b0;
        ROM[7] <= 32'b0;
        ROM[8] <= 32'b0;
        ROM[9] <= 32'b0;
        ROM[10] <= 32'b0;
        ROM[11] <= 32'b0;
        ROM[12] <= 32'b0;
        ROM[13] <= 32'b0;
        ROM[14] <= 32'b0;
        ROM[15] <= 32'b0;
    end


    assign RD1 = ROM[A1];
    assign RD2 = ROM[A2];
    // RegWrite is set to 1 when lw Instr is executed
    always @(posedge clk) begin
        A <= RD1;
        B <= RD2;
        if (RegWrite) begin
            // load word
            ROM[A3] <= WD3;
        end
    end
endmodule

MIPS_Multi_Cycle/Control_Unit.v
/*

	File name    : 
	LastEditors  : H
	LastEditTime : 2021-10-28 20:59:03
	Last Version : 1.0
	Description  : 
	
	----------------------------------------------------------------------------------------
	
	Author       : H
	Date         : 2021-10-28 20:59:02
	FilePath     : \MIPS_Single\Control_Unit.v
	Copyright 2021 H, All Rights Reserved. 

*/
module Control_Unit(
    // System Clock
    input        clk,
    input        rst_n,

    // User Interface

    input       [5:0]   Opcode,

    output  reg [1:0]   ALUOp,
    output  reg         MemtoReg,
    output  reg         RegDst,
    output  reg         IorD,
    output  reg [1:0]   PCSrc,
    output  reg [1:0]   ALUSrcB,
    output  reg         ALUSrcA,

    output  reg         IRWrite,
    output  reg         MemWrite,
    output  reg         PCWrite,
    output  reg         Branch,
    output  reg         RegWrite
);

    parameter   S0_Fetch   = 4'd0, S1_Decode       = 4'd1, S2_MemAdr   = 4'd2;
    parameter   S3_MemRead = 4'd3, S4_MemWriteback = 4'd4, S5_MemWrite = 4'd5;
    parameter   S6_Execute = 4'd6, S7_ALU_Writeback= 4'd7, S8_Branch   = 4'd8;
    parameter   S9_ADDI    = 4'd9, S10_ADDI_Writeback=4'd10,S11_Jump   = 4'd11;
    reg [3:0]   Current_State, Next_State;  

/*******************************************************************************
 *                                 Main Code
*******************************************************************************/

    always @(*) begin
        case(Current_State)
            S0_Fetch : begin
                IorD    = 1'b0;
                ALUSrcA = 1'b0;
                ALUSrcB = 2'b01;
                ALUOp   = 2'b00;
                PCSrc   = 2'b00;


                IRWrite = 1'b1;
                MemWrite= 1'b0;
                PCWrite = 1'b1;
                Branch  = 1'b0;
                RegWrite= 1'b0;
            end
            S1_Decode : begin
                ALUSrcA = 1'b0;
                ALUSrcB = 2'b11;
                ALUOp   = 2'b00;

                IRWrite = 1'b0;
                MemWrite= 1'b0;
                PCWrite = 1'b0;
                Branch  = 1'b0;
                RegWrite= 1'b0;
            end
            S2_MemAdr : begin
                ALUSrcA = 1'b1;
                ALUSrcB = 2'b10;
                ALUOp   = 2'b00;

                IRWrite  = 1'b0;
                MemWrite = 1'b0;
                PCWrite  = 1'b0;
                Branch   = 1'b0;
                RegWrite = 1'b0;
            end
            S3_MemRead : begin
                IorD     = 1'b1;

                IRWrite  = 1'b0;
                MemWrite = 1'b0;
                PCWrite  = 1'b0;
                Branch   = 1'b0;
                RegWrite = 1'b0;
            end
            S4_MemWriteback : begin
                RegDst   = 1'b0;
                MemtoReg = 1'b1;

                IRWrite  = 1'b0;
                MemWrite = 1'b0;
                PCWrite  = 1'b0;
                Branch   = 1'b0;
                RegWrite = 1'b1;
            end
            S5_MemWrite : begin
                IorD     = 1'b1;

                IRWrite  = 1'b0;
                MemWrite = 1'b1;
                PCWrite  = 1'b0;
                Branch   = 1'b0;
                RegWrite = 1'b0;
            end
            S6_Execute : begin
                ALUSrcA  = 1'b1;
                ALUSrcB  = 2'b00;
                ALUOp    = 2'b10;

                IRWrite  = 1'b0;
                MemWrite = 1'b0;
                PCWrite  = 1'b0;
                Branch   = 1'b0;
                RegWrite = 1'b0;
            end
            S7_ALU_Writeback : begin
                RegDst   = 1'b1;
                MemtoReg = 1'b0;

                IRWrite  = 1'b0;
                MemWrite = 1'b0;
                PCWrite  = 1'b0;
                Branch   = 1'b0;
                RegWrite = 1'b1;
            end
            S8_Branch : begin
                ALUSrcA  = 1'b1;
                ALUSrcB  = 2'b00;
                ALUOp    = 2'b01;
                PCSrc    = 2'b01; 

                IRWrite  = 1'b0;
                MemWrite = 1'b0;
                PCWrite  = 1'b0;
                Branch   = 1'b1;
                RegWrite = 1'b0;
            end
            S9_ADDI : begin
                ALUSrcA  = 1'b1;
                ALUSrcB  = 2'b10;
                ALUOp    = 2'b00;

                IRWrite  = 1'b0;
                MemWrite = 1'b0;
                PCWrite  = 1'b0;
                Branch   = 1'b0;
                RegWrite = 1'b0;
            end
            S10_ADDI_Writeback : begin
                RegDst   = 1'b0;
                MemtoReg = 1'b0;

                IRWrite  = 1'b0;
                MemWrite = 1'b0;
                PCWrite  = 1'b0;
                Branch   = 1'b0;
                RegWrite = 1'b1;
            end
            S11_Jump : begin
                PCSrc    = 2'b10;

                IRWrite  = 1'b0;
                MemWrite = 1'b0;
                PCWrite  = 1'b1;
                Branch   = 1'b0;
                RegWrite = 1'b0;
            end
        endcase 
    end

    always @(*) begin
        case(Current_State)
            S0_Fetch : Next_State = S1_Decode;
            S1_Decode : begin
                case(Opcode)
                    // OP = lw or sw
                    6'b100011,6'b101011 : Next_State = S2_MemAdr;
                    // Op = R-type
                    6'b000000: Next_State = S6_Execute;
                    // Op = Beq
                    6'b000100: Next_State = S8_Branch;
                    // Op = addi
                    6'b001000: Next_State = S9_ADDI;
                    // Op = Jump
                    6'b000010: Next_State = S11_Jump;
                endcase 
            end
            S2_MemAdr : begin
                case (Opcode)
                    6'b100011: Next_State = S3_MemRead;
                    6'b101011: Next_State = S5_MemWrite;
                    
                    default: ;
                endcase
            end
            S3_MemRead      : Next_State = S4_MemWriteback;
            S4_MemWriteback : Next_State = S0_Fetch;
            S5_MemWrite     : Next_State = S0_Fetch;
            S6_Execute      : Next_State = S7_ALU_Writeback;
            S7_ALU_Writeback: Next_State = S0_Fetch;
            S8_Branch       : Next_State = S0_Fetch;
            S9_ADDI         : Next_State = S10_ADDI_Writeback;
            S10_ADDI_Writeback : Next_State = S0_Fetch;
            S11_Jump        : Next_State = S0_Fetch;
        endcase
    end

    always @(posedge clk) begin
        if (!rst_n) begin
            Current_State <= S0_Fetch;
        end
        else begin
            Current_State <= Next_State;
        end
    end

endmodule

MIPS_Multi_Cycle/Instr_Data_Memory.v
/*

	File name    : Instr_Data_Memory
	LastEditors  : H
	LastEditTime : 2021-11-01 11:10:05
	Last Version : 1.0
	Description  : 
	
	----------------------------------------------------------------------------------------
	
	Author       : H
	Date         : 2021-10-31 13:48:53
	FilePath     : \MIPS_Multi_Cycle\Instr_Data_Memory.v
	Copyright 2021 H, All Rights Reserved. 

*/
module Instr_Data_Memory(
    // System Clock
	input				clk,
    input   	[31:0]	A,
	input		[31:0]	WD,
	input				IRWrite,
	input				MemWrite,

	output	reg	[31:0]	Instr,
	output	reg	[31:0]	Data
    // User Interface
    
);
	integer fd;
	wire [31:0] RD;
	reg [7:0] Instr_Data_Mem [84:0];

/*******************************************************************************
 *                                 Main Code
*******************************************************************************/

	initial begin
		$readmemh("./memfile.dat",Instr_Data_Mem,0,71);
		fd = $fopen("./MEM_Data.txt", "w");  
        #1400
        $fclose(fd);
	end

    assign RD = {{Instr_Data_Mem[A]},{Instr_Data_Mem[A+32'd1]},{Instr_Data_Mem[A+32'd2]},{Instr_Data_Mem[A+32'd3]}};

	always @(posedge clk) begin
		Data <= RD;
		if (IRWrite) begin
			Instr <= RD;
		end
		// Notice : the signal A now is Data Address here
		if (MemWrite) begin
			{{Instr_Data_Mem[A]},{Instr_Data_Mem[A+32'd1]},{Instr_Data_Mem[A+32'd2]},{Instr_Data_Mem[A+32'd3]}} <= WD;
			$fdisplay(fd,"The Write Address A is %h", A);
            $fdisplay(fd,"DATA_MEM[A] is %h", WD);
		end
	end
endmodule

MIPS_Multi_Cycle/PC_Counter.v
/*

	File name    : 
	LastEditors  : H
	LastEditTime : 2021-10-28 21:36:58
	Last Version : 1.0
	Description  : 
	
	----------------------------------------------------------------------------------------
	
	Author       : H
	Date         : 2021-10-28 21:36:57
	FilePath     : \MIPS_Single\PC_Counter.v
	Copyright 2021 H, All Rights Reserved. 

*/
module PC_Counter(
    // System Clock
    input                       clk,
    input                       rst_n,

    // User Interface
    input                       PCEn,
    input                       IorD,   // Instruction or Data
    input               [1:0]   PCSrc,
    input               [25:0]  Jump_low_26Bit,
    input               [31:0]  ALUOut,
    input               [31:0]  ALUResult,
    output              [31:0]  Adr,
    output  reg         [31:0]  PC
);
    reg                 [31:0]  PC_Next;

/*******************************************************************************
 *                                 Main Code
*******************************************************************************/

    assign Adr = IorD ? ALUOut : PC;
    // MIPS Multi Cycle: Use ALU to Calculate the PC + 4
    always @(*) begin
        case(PCSrc)
            2'b00: PC_Next = ALUResult;
            2'b01: PC_Next = ALUOut;
            2'b10: PC_Next = {{PC[31:28]}, {Jump_low_26Bit}, 2'b00};
        endcase
    end

    always @(posedge clk) begin
        if(~rst_n)begin
            PC <= 32'b0;
        end
        else if (PCEn) begin
            // here PC_Next need to change
            PC <= PC_Next;
        end
    end

endmodule

MIPS_Multi_Cycle/MIPS_Multi_Cycle.v
/*

	File name    : MIPS_Multi_Cycle
	LastEditors  : H
	LastEditTime : 2021-11-01 12:54:34
	Last Version : 1.0
	Description  : 
	
	----------------------------------------------------------------------------------------
	
	Author       : H
	Date         : 2021-10-31 13:48:53
	FilePath     : \MIPS_Multi_Cycle\MIPS_Multi_Cycle.v
	Copyright 2021 H, All Rights Reserved. 

*/
module MIPS_Multi_Cycle(
    // System Clock
    input               clk,
    input               rst_n

    // User Interface
    
);
    wire [31:0]         PC;
    wire [31:0]         ALUResult;
    wire [31:0]         SignImm;
    wire [31:0]         ALUOut;
    wire [31:0]         Instr;
    wire [31:0]         Data;
    wire [31:0]         A,B;
    wire [31:0]         Adr;
    wire [31:0]         WriteRegData;
    
    wire [2:0]          ALUControl;
    wire [1:0]          ALUOp;
    wire [1:0]          PCSrc;
    wire [4:0]          WriteReg;
    wire [1:0]          ALUSrcB;
    wire                ALUSrcA;     

    wire                MemWrite, RegWrite, IorD;
    wire                RegDst, ALUSrc, MemtoReg;
    wire                Branch, Zero;
    wire                PCEn, PCWrite, IRWrite;
    
/*******************************************************************************
 *                                 Main Code
*******************************************************************************/

    assign PCEn         = (Branch & Zero) | PCWrite;

    assign WriteReg     = RegDst ? Instr[15:11] : Instr[20:16];
    assign WriteRegData = MemtoReg ? Data : ALUOut;

    PC_Counter u_PC_Counter(
        .clk            (clk),
        .rst_n          (rst_n),
        .PCSrc          (PCSrc),
        .PCEn           (PCEn),
        .IorD           (IorD),
        .ALUOut         (ALUOut),
        .ALUResult      (ALUResult),
        .Jump_low_26Bit (Instr[25:0]),
        .Adr            (Adr),
        .PC             (PC)
    );

    Instr_Data_Memory u_Instr_Data_Memory(
        .clk            (clk),
        .A              (Adr),
        .WD             (B),
        .IRWrite        (IRWrite),
        .MemWrite       (MemWrite),
        .Instr          (Instr),
        .Data           (Data)
    );

    Control_Unit u_Control_Unit(
        .clk            (clk),
        .rst_n          (rst_n),
        .Opcode         (Instr[31:26]),
        .ALUOp          (ALUOp),
        .MemtoReg       (MemtoReg),
        .RegDst         (RegDst),
        .IorD           (IorD),
        .PCSrc          (PCSrc),
        .ALUSrcA        (ALUSrcA),
        .ALUSrcB        (ALUSrcB),
        .IRWrite        (IRWrite),
        .MemWrite       (MemWrite),
        .PCWrite        (PCWrite),
        .Branch         (Branch),
        .RegWrite       (RegWrite)
    );

    Reg_File u_Reg_File(
        .clk            (clk),
        .A1             (Instr[25:21]),
        .A2             (Instr[20:16]),
        .A3             (WriteReg),
        .A              (A),
        .B              (B),
        .RegWrite       (RegWrite),
        .WD3            (WriteRegData)
    );

    Imm_Sign_Extend u_Imm_Sign_Extend(
        .Immediate      (Instr[15:0]),
        .SignImm        (SignImm)
    );


    ALU_Control_Unit u_ALU_Control_Unit(
        .Funct          (Instr[5:0]),
        .ALUOp          (ALUOp),
        .ALUControl     (ALUControl)
    );

    ALU u_ALU(
        .clk            (clk),
        .ALUSrcA        (ALUSrcA),
        .ALUSrcB        (ALUSrcB),
        .ALUControl     (ALUControl),
        .A              (A),
        .B              (B),
        .PC             (PC),
        .SignImm        (SignImm),
        .ALUOut         (ALUOut),
        .ALUResult      (ALUResult),
        .Zero           (Zero)
    );

endmodule

MIPS_Multi_Cycle/tb_MIPS_Multi_Cycle.v
/*

	File name    : tb_MIPS_Multi_Cycle
	LastEditors  : H
	LastEditTime : 2021-11-01 15:13:21
	Last Version : 1.0
	Description  : 
	
	----------------------------------------------------------------------------------------
	
	Author       : H
	Date         : 2021-10-31 13:48:53
	FilePath     : \MIPS_Multi_Cycle\tb_MIPS_Multi_Cycle.v
	Copyright 2021 H, All Rights Reserved. 

*/
`timescale 1ps/1ps
module tb_MIPS_Multi_Cycle();

reg clk,rst_n;
reg [31:0] cnt;

/*******************************************************************************
 *                                 Main Code
*******************************************************************************/

initial
begin            
    $dumpfile("MIPS_wave.vcd");        
    $dumpvars(0, tb_MIPS_Multi_Cycle);    
end

initial begin
    clk     <= 1'b0;
    rst_n   <= 1'b0;
    cnt     <= 32'b0;

    #10
    clk     <= 1'b1;

    #10
    clk     <= 1'b0;
    rst_n   <= 1'b1;

    forever begin
        #10 clk <= ~clk;
    end
end

always @(negedge clk) begin
    cnt <= cnt + 1'b1;
    if (cnt >= 72) begin
        $stop;
    end
end

MIPS_Multi_Cycle u_MIPS_Multi_Cycle(
    .clk(clk),
    .rst_n(rst_n)
);

endmodule

MIPS_Multi_Cycle/MIPS_wave.vcd
$date
	Sat Nov 06 16:47:57 2021
$end
$version
	Icarus Verilog
$end
$timescale
	1ps
$end
$scope module tb_MIPS_Multi_Cycle $end
$var reg 1 ! clk $end
$var reg 32 " cnt [31:0] $end
$var reg 1 # rst_n $end
$scope module u_MIPS_Multi_Cycle $end
$var wire 1 $ PCEn $end
$var wire 1 ! clk $end
$var wire 1 # rst_n $end
$var wire 1 % Zero $end
$var wire 32 & WriteRegData [31:0] $end
$var wire 5 ' WriteReg [4:0] $end
$var wire 32 ( SignImm [31:0] $end
$var wire 1 ) RegWrite $end
$var wire 1 * RegDst $end
$var wire 1 + PCWrite $end
$var wire 2 , PCSrc [1:0] $end
$var wire 32 - PC [31:0] $end
$var wire 1 . MemtoReg $end
$var wire 1 / MemWrite $end
$var wire 1 0 IorD $end
$var wire 32 1 Instr [31:0] $end
$var wire 1 2 IRWrite $end
$var wire 32 3 Data [31:0] $end
$var wire 1 4 Branch $end
$var wire 32 5 B [31:0] $end
$var wire 32 6 Adr [31:0] $end
$var wire 2 7 ALUSrcB [1:0] $end
$var wire 1 8 ALUSrcA $end
$var wire 32 9 ALUResult [31:0] $end
$var wire 32 : ALUOut [31:0] $end
$var wire 2 ; ALUOp [1:0] $end
$var wire 3 < ALUControl [2:0] $end
$var wire 32 = A [31:0] $end
$scope module u_ALU $end
$var wire 1 ! clk $end
$var wire 1 % Zero $end
$var wire 32 > SignImm [31:0] $end
$var wire 32 ? PC [31:0] $end
$var wire 32 @ B [31:0] $end
$var wire 2 A ALUSrcB [1:0] $end
$var wire 1 8 ALUSrcA $end
$var wire 3 B ALUControl [2:0] $end
$var wire 32 C A [31:0] $end
$var reg 32 D ALUOut [31:0] $end
$var reg 32 E ALUResult [31:0] $end
$var reg 32 F SrcA [31:0] $end
$var reg 32 G SrcB [31:0] $end
$upscope $end
$scope module u_ALU_Control_Unit $end
$var wire 6 H Funct [5:0] $end
$var wire 2 I ALUOp [1:0] $end
$var reg 3 J ALUControl [2:0] $end
$upscope $end
$scope module u_Control_Unit $end
$var wire 6 K Opcode [5:0] $end
$var wire 1 ! clk $end
$var wire 1 # rst_n $end
$var reg 2 L ALUOp [1:0] $end
$var reg 1 8 ALUSrcA $end
$var reg 2 M ALUSrcB [1:0] $end
$var reg 1 4 Branch $end
$var reg 4 N Current_State [3:0] $end
$var reg 1 2 IRWrite $end
$var reg 1 0 IorD $end
$var reg 1 / MemWrite $end
$var reg 1 . MemtoReg $end
$var reg 4 O Next_State [3:0] $end
$var reg 2 P PCSrc [1:0] $end
$var reg 1 + PCWrite $end
$var reg 1 * RegDst $end
$var reg 1 ) RegWrite $end
$upscope $end
$scope module u_Imm_Sign_Extend $end
$var wire 16 Q Immediate [15:0] $end
$var wire 32 R SignImm [31:0] $end
$upscope $end
$scope module u_Instr_Data_Memory $end
$var wire 1 2 IRWrite $end
$var wire 1 / MemWrite $end
$var wire 1 ! clk $end
$var wire 32 S WD [31:0] $end
$var wire 32 T RD [31:0] $end
$var wire 32 U A [31:0] $end
$var reg 32 V Data [31:0] $end
$var reg 32 W Instr [31:0] $end
$var integer 32 X fd [31:0] $end
$upscope $end
$scope module u_PC_Counter $end
$var wire 32 Y ALUOut [31:0] $end
$var wire 32 Z ALUResult [31:0] $end
$var wire 1 0 IorD $end
$var wire 26 [ Jump_low_26Bit [25:0] $end
$var wire 1 $ PCEn $end
$var wire 2 \ PCSrc [1:0] $end
$var wire 1 ! clk $end
$var wire 1 # rst_n $end
$var wire 32 ] Adr [31:0] $end
$var reg 32 ^ PC [31:0] $end
$var reg 32 _ PC_Next [31:0] $end
$upscope $end
$scope module u_Reg_File $end
$var wire 5 ` A1 [4:0] $end
$var wire 5 a A2 [4:0] $end
$var wire 5 b A3 [4:0] $end
$var wire 32 c RD1 [31:0] $end
$var wire 32 d RD2 [31:0] $end
$var wire 1 ) RegWrite $end
$var wire 32 e WD3 [31:0] $end
$var wire 1 ! clk $end
$var reg 32 f A [31:0] $end
$var reg 32 g B [31:0] $end
$upscope $end
$upscope $end
$upscope $end
$enddefinitions $end
#0
$dumpvars
bx g
bx f
bx e
bx d
bx c
bx b
bx a
bx `
bx _
bx ^
bx ]
bx \
bx [
bx Z
bx Y
b10000000000000000000000000000011 X
bx W
bx V
bx U
bx T
bx S
bx R
bx Q
bx P
bx O
bx N
bx M
bx L
bx K
bx J
bx I
bx H
bx G
bx F
bx E
bx D
bx C
bx B
bx A
bx @
bx ?
bx >
bx =
bx <
bx ;
bx :
bx 9
x8
bx 7
bx 6
bx 5
x4
bx 3
x2
bx 1
x0
x/
x.
bx -
bx ,
x+
x*
x)
bx (
bx '
bx &
x%
x$
0#
b1 "
0!
$end
#10
0%
b100 _
b100 9
b100 E
b100 Z
1$
b10 <
b10 B
b10 J
b100000000000100000000000000101 T
b0 6
b0 U
b0 ]
b100 G
b0 F
b1 O
0)
04
1+
0/
12
b0 ,
b0 P
b0 \
b0 ;
b0 I
b0 L
b1 7
b1 A
b1 M
08
00
b0 -
b0 ?
b0 ^
b0 N
1!
#20
b10 "
1#
0!
#30
0%
0$
b10100 G
b11000 _
b0x0 '
b0x0 b
b11000 9
b11000 E
b11000 Z
b1001 O
0+
02
b11 7
b11 A
b11 M
b101 H
b101 (
b101 >
b101 R
b101 Q
b0 d
b10 a
b0 c
b0 `
b1000 K
b100000000000000101 [
b0x00000000000x0000000000000010x &
b0x00000000000x0000000000000010x e
b100000000000110000000000001100 T
b100 6
b100 U
b100 ]
b100 F
b100 :
b100 D
b100 Y
b1 N
b100000000000100000000000000101 1
b100000000000100000000000000101 W
b100000000000100000000000000101 3
b100000000000100000000000000101 V
b100 -
b100 ?
b100 ^
1!
#40
b11 "
0!
#50
b101 _
b101 9
b101 E
b101 Z
b101 G
b0 F
b1010 O
b10 7
b10 A
b10 M
18
b0x00000000000xx00000000000x1x00 &
b0x00000000000xx00000000000x1x00 e
b100000000000110000000000001100 3
b100000000000110000000000001100 V
b1001 N
b0 5
b0 @
b0 S
b0 g
b0 =
b0 C
b0 f
b11000 :
b11000 D
b11000 Y
1!
#60
b100 "
0!
#70
b10 '
b10 b
b101 &
b101 e
b0 O
1)
0.
0*
b101 :
b101 D
b101 Y
b1010 N
1!
#80
b101 "
0!
#90
b1000 _
b1000 9
b1000 E
b1000 Z
1$
b100 G
b100 F
b1 O
0)
1+
12
b1 7
b1 A
b1 M
08
b0 N
b101 d
1!
#100
b110 "
0!
#110
0$
b110000 G
b111000 _
b11 '
b11 b
b111000 9
b111000 E
b111000 Z
b1000 &
b1000 e
b1001 O
0+
02
b11 7
b11 A
b11 M
b1100 H
b1100 (
b1100 >
b1100 R
b1100 Q
b0 d
b11 a
b110000000000001100 [
b100000011001111111111111110111 T
b1000 6
b1000 U
b1000 ]
b1000 F
b1000 :
b1000 D
b1000 Y
b101 5
b101 @
b101 S
b101 g
b1 N
b100000000000110000000000001100 1
b100000000000110000000000001100 W
b1000 -
b1000 ?
b1000 ^
1!
#120
b111 "
0!
#130
b1100 _
b1100 9
b1100 E
b1100 Z
b1100 G
b0 F
b1010 O
b10 7
b10 A
b10 M
18
b111000 &
b111000 e
b100000011001111111111111110111 3
b100000011001111111111111110111 V
b1001 N
b0 5
b0 @
b0 S
b0 g
b111000 :
b111000 D
b111000 Y
1!
#140
b1000 "
0!
#150
b1100 &
b1100 e
b0 O
1)
b1100 :
b1100 D
b1100 Y
b1010 N
1!
#160
b1001 "
0!
#170
1$
b100 G
b1000 F
b1 O
0)
1+
12
b1 7
b1 A
b1 M
08
b0 N
b1100 d
1!
#180
b1010 "
0!
#190
0$
b11111111111111111111111111011100 G
b11111111111111111111111111101000 _
b111 '
b111 b
b11111111111111111111111111101000 9
b11111111111111111111111111101000 E
b11111111111111111111111111101000 Z
b1001 O
0+
02
b11 7
b11 A
b11 M
b110111 H
b11111111111111111111111111110111 (
b11111111111111111111111111110111 >
b11111111111111111111111111110111 R
b1111111111110111 Q
b0 d
b111 a
b1100 c
b11 `
b11001111111111111110111 [
b111000100010000000100101 T
b1100 6
b1100 U
b1100 ]
b1100 F
b1100 5
b1100 @
b1100 S
b1100 g
b1 N
b100000011001111111111111110111 1
b100000011001111111111111110111 W
b1100 -
b1100 ?
b1100 ^
1!
#200
b1011 "
0!
#210
b11 _
b11 9
b11 E
b11 Z
b11111111111111111111111111110111 G
b1010 O
b10 7
b10 A
b10 M
18
b11111111111111111111111111101000 &
b11111111111111111111111111101000 e
b111000100010000000100101 3
b111000100010000000100101 V
b1001 N
b0 5
b0 @
b0 S
b0 g
b1100 =
b1100 C
b1100 f
b11111111111111111111111111101000 :
b11111111111111111111111111101000 D
b11111111111111111111111111101000 Y
1!
#220
b1100 "
0!
#230
b11 &
b11 e
b0 O
1)
b11 :
b11 D
b11 Y
b1010 N
1!
#240
b1101 "
0!
#250
b10000 _
b10000 9
b10000 E
b10000 Z
1$
b100 G
b1 O
0)
1+
12
b1 7
b1 A
b1 M
08
b0 N
b11 d
1!
#260
b1110 "
0!
#270
0$
b1000000010010100 G
b1000000010100100 _
b10 '
b10 b
b1000000010100100 9
b1000000010100100 E
b1000000010100100 Z
b10000 &
b10000 e
b110 O
0+
02
b11 7
b11 A
b11 M
b100101 H
b10000000100101 (
b10000000100101 >
b10000000100101 R
b10000000100101 Q
b101 d
b10 a
b11 c
b111 `
b0 K
b111000100010000000100101 [
b11001000010100000100100 T
b10000 6
b10000 U
b10000 ]
b10000 F
b10000 :
b10000 D
b10000 Y
b11 5
b11 @
b11 S
b11 g
b1 N
b111000100010000000100101 1
b111000100010000000100101 W
b10000 -
b10000 ?
b10000 ^
1!
#280
b1111 "
0!
#290
b111 _
b111 9
b111 E
b111 Z
b1 <
b1 B
b1 J
b101 G
b11 F
b111 O
b10 ;
b10 I
b10 L
b0 7
b0 A
b0 M
18
b1000000010100100 &
b1000000010100100 e
b11001000010100000100100 3
b11001000010100000100100 V
b110 N
b101 5
b101 @
b101 S
b101 g
b11 =
b11 C
b11 f
b1000000010100100 :
b1000000010100100 D
b1000000010100100 Y
1!
#300
b10000 "
0!
#310
b100 '
b100 b
b111 &
b111 e
b0 O
1)
1*
b111 :
b111 D
b111 Y
b111 N
1!
#320
b10001 "
0!
#330
b10100 _
b10100 9
b10100 E
b10100 Z
1$
b10 <
b10 B
b10 J
b100 G
b10000 F
b1 O
0)
1+
12
b0 ;
b0 I
b0 L
b1 7
b1 A
b1 M
08
b0 N
1!
#340
b10010 "
0!
#350
0$
b1010000010010000 G
b1010000010100100 _
b101 '
b101 b
b1010000010100100 9
b1010000010100100 E
b1010000010100100 Z
b10100 &
b10100 e
b110 O
0+
02
b11 7
b11 A
b11 M
b100100 H
b10100000100100 (
b10100000100100 >
b10100000100100 R
b10100000100100 Q
b111 d
b100 a
b1100 c
b11 `
b11001000010100000100100 [
b101001000010100000100000 T
b10100 6
b10100 U
b10100 ]
b10100 F
b10100 :
b10100 D
b10100 Y
b1 N
b11001000010100000100100 1
b11001000010100000100100 W
b10100 -
b10100 ?
b10100 ^
1!
#360
b10011 "
0!
#370
b100 _
b100 9
b100 E
b100 Z
b0 <
b0 B
b0 J
b111 G
b1100 F
b111 O
b10 ;
b10 I
b10 L
b0 7
b0 A
b0 M
18
b1010000010100100 &
b1010000010100100 e
b101001000010100000100000 3
b101001000010100000100000 V
b110 N
b111 5
b111 @
b111 S
b111 g
b1100 =
b1100 C
b1100 f
b1010000010100100 :
b1010000010100100 D
b1010000010100100 Y
1!
#380
b10100 "
0!
#390
b100 &
b100 e
b0 O
1)
b100 :
b100 D
b100 Y
b111 N
1!
#400
b10101 "
0!
#410
b11000 _
b11000 9
b11000 E
b11000 Z
1$
b10 <
b10 B
b10 J
b100 G
b10100 F
b1 O
0)
1+
12
b0 ;
b0 I
b0 L
b1 7
b1 A
b1 M
08
b0 N
1!
#420
b10110 "
0!
